automizor/__init__.py
automizor/exceptions.py
automizor/utils.py
automizor/action/__init__.py
automizor/action/_action.py
automizor/counter/__init__.py
automizor/counter/_counter.py
automizor/datastore/__init__.py
automizor/datastore/_container.py
automizor/datastore/_datastore.py
automizor/job/__init__.py
automizor/job/_job.py
automizor/storage/__init__.py
automizor/storage/_storage.py
automizor/vault/__init__.py
automizor/vault/_container.py
automizor/vault/_vault.py
automizor/workflow/__init__.py
automizor/workflow/_workflow.py
automizor-0.4.21.dist-info/licenses/LICENSE
automizor-0.4.21.dist-info/METADATA
automizor-0.4.21.dist-info/WHEEL
automizor-0.4.21.dist-info/top_level.txt
automizor-0.4.21.dist-info/RECORD
